datasets/__init__.py
deepforecast/__init__.py
deepforecast/cores/__init__.py
deepforecast/cores/utils/__init__.py
deepforecast/features/__init__.py
deepforecast/layers/__init__.py
deepforecast/layers/core.py
deepforecast/layers/seq2seq.py
deepforecast/models/__init__.py
deepforecast/models/attention_seq2seq.py
deepforecast/models/base.py
deepforecast/models/deepar.py
deepforecast/models/mqrnn.py
deepforecast/models/seq2seq.py
deepforecast/models/sttf.py
test/__init__.py
test/test_seq2seq.py
test/test_sttf.py
deepforecast-0.0.1.dist-info/LICENSE
deepforecast-0.0.1.dist-info/METADATA
deepforecast-0.0.1.dist-info/WHEEL
deepforecast-0.0.1.dist-info/top_level.txt
deepforecast-0.0.1.dist-info/RECORD
